bing_hashing_image_downloader/__init__.py
bing_hashing_image_downloader/bing.py
bing_hashing_image_downloader/downloader.py
bing_hashing_image_downloader-22.8.24.1326.dist-info/LICENSE
bing_hashing_image_downloader-22.8.24.1326.dist-info/METADATA
bing_hashing_image_downloader-22.8.24.1326.dist-info/WHEEL
bing_hashing_image_downloader-22.8.24.1326.dist-info/top_level.txt
bing_hashing_image_downloader-22.8.24.1326.dist-info/RECORD
