Metadata-Version: 2.1
Name: bing-hashing-image-downloader
Version: 22.8.24.1326
Summary: Python library to download bulk images from Bing.com without repeated images
Home-page: https://github.com/korreckj328/bing_hashing_image_downloader
Author: Jeremiah Korreck (fork), Guru Prasad Singh (original)
Author-email: korreckj328@gmail.com
Keywords: bing,images,scraping,image download,bulk image downloader,sha1
Classifier: Programming Language :: Python :: 3
Classifier: License :: OSI Approved :: MIT License
Classifier: Operating System :: OS Independent
License-File: LICENSE
